gemasearch/__init__.py
gemasearch/data.py
gemasearch/search.py
pygemasearch-0.1.4.dist-info/licenses/LICENSE
tests/__init__.py
tests/search_test.py
pygemasearch-0.1.4.dist-info/METADATA
pygemasearch-0.1.4.dist-info/WHEEL
pygemasearch-0.1.4.dist-info/entry_points.txt
pygemasearch-0.1.4.dist-info/top_level.txt
pygemasearch-0.1.4.dist-info/RECORD
