Metadata-Version: 2.4
Name: PyGEMASearch
Version: 0.1.4
Summary: A Python package to search for songs in the GEMA database.
Home-page: https://github.com/DonMikone/PyGEMASearch
Author: Mike Kremer
Author-email: mikelsoft@gmail.com
Classifier: Programming Language :: Python :: 3
Classifier: License :: OSI Approved :: MIT License
Classifier: Operating System :: OS Independent
Requires-Python: >=3.6
License-File: LICENSE
Requires-Dist: requests
Dynamic: author
Dynamic: author-email
Dynamic: classifier
Dynamic: description
Dynamic: description-content-type
Dynamic: home-page
Dynamic: license-file
Dynamic: requires-dist
Dynamic: requires-python
Dynamic: summary
